rebase/__init__.py
rebase/error.py
rebase/api/__init__.py
rebase/api/backend.py
rebase/api/predicter.py
rebase/api/runner.py
rebase/api/site.py
rebase/api/weather.py
rebase/util/__init__.py
rebase/util/api_request.py
rebase_toolkit-0.0.4b0.dist-info/LICENSE
rebase_toolkit-0.0.4b0.dist-info/METADATA
rebase_toolkit-0.0.4b0.dist-info/WHEEL
rebase_toolkit-0.0.4b0.dist-info/top_level.txt
rebase_toolkit-0.0.4b0.dist-info/RECORD
